{"nodes": [{"id": "940GZZLUBST", "lat": 51.52288, "lon": -0.15713, "name": "Baker Street"}, {"id": "940GZZLUCHX", "lat": 51.50741, "lon": -0.12728, "name": "Charing Cross"}, {"id": "940GZZLUEAC", "lat": 51.49454, "lon": -0.10061, "name": "Elephant & Castle"}, {"id": "940GZZLUEMB", "lat": 51.50706, "lon": -0.12267, "name": "Embankment"}, {"id": "940GZZLUERB", "lat": 51.5203, "lon": -0.17015, "name": "Edgware Road (Bakerloo)"}, {"id": "940GZZLUHAW", "lat": 51.59227, "lon": -0.33522, "name": "Harrow & Wealdstone"}, {"id": "940GZZLUHSN", "lat": 51.53631, "lon": -0.25788, "name": "Harlesden"}, {"id": "940GZZLUKEN", "lat": 51.58176, "lon": -0.31691, "name": "Kenton"}, {"id": "940GZZLUKPK", "lat": 51.53498, "lon": -0.19423, "name": "Kilburn Park"}, {"id": "940GZZLUKSL", "lat": 51.53054, "lon": -0.22502, "name": "Kensal Green"}, {"id": "940GZZLULBN", "lat": 51.49881, "lon": -0.11231, "name": "Lambeth North"}, {"id": "940GZZLUMVL", "lat": 51.52978, "lon": -0.18576, "name": "Maida Vale"}, {"id": "940GZZLUMYB", "lat": 51.52232, "lon": -0.16321, "name": "Marylebone"}, {"id": "940GZZLUNWY", "lat": 51.56255, "lon": -0.304, "name": "North Wembley"}, {"id": "940GZZLUOXC", "lat": 51.51522, "lon": -0.1419, "name": "Oxford Circus"}, {"id": "940GZZLUPAC", "lat": 51.51658, "lon": -0.17569, "name": "Paddington"}, {"id": "940GZZLUPCC", "lat": 51.51005, "lon": -0.1338, "name": "Piccadilly Circus"}, {"id": "940GZZLUQPS", "lat": 51.53416, "lon": -0.20457, "name": "Queen's Park"}, {"id": "940GZZLURGP", "lat": 51.52334, "lon": -0.14644, "name": "Regent's Park"}, {"id": "940GZZLUSGP", "lat": 51.54396, "lon": -0.27589, "name": "Stonebridge Park"}, {"id": "940GZZLUSKT", "lat": 51.57023, "lon": -0.30843, "name": "South Kenton"}, {"id": "940GZZLUWJN", "lat": 51.53226, "lon": -0.24428, "name": "Willesden Junction"}, {"id": "940GZZLUWKA", "lat": 51.52326, "lon": -0.18378, "name": "Warwick Avenue"}, {"id": "940GZZLUWLO", "lat": 51.5033, "lon": -0.11478, "name": "Waterloo"}, {"id": "940GZZLUWYC", "lat": 51.5523, "lon": -0.29685, "name": "Wembley Central"}, {"id": "940GZZLUBKE", "lat": 51.58569, "lon": 0.08858, "name": "Barkingside"}, {"id": "940GZZLUBKH", "lat": 51.6266, "lon": 0.04676, "name": "Buckhurst Hill"}, {"id": "940GZZLUBLG", "lat": 51.52722, "lon": -0.05551, "name": "Bethnal Green"}, {"id": "940GZZLUBND", "lat": 51.5143, "lon": -0.14972, "name": "Bond Street"}, {"id": "940GZZLUBNK", "lat": 51.51313, "lon": -0.09005, "name": "Bank"}, {"id": "940GZZLUCHL", "lat": 51.51825, "lon": -0.11158, "name": "Chancery Lane"}, {"id": "940GZZLUCWL", "lat": 51.61792, "lon": 0.07504, "name": "Chigwell"}, {"id": "940GZZLUDBN", "lat": 51.64539, "lon": 0.08378, "name": "Debden"}, {"id": "940GZZLUEAN", "lat": 51.51661, "lon": -0.24725, "name": "East Acton"}, {"id": "940GZZLUEBY", "lat": 51.51502, "lon": -0.30146, "name": "Ealing Broadway"}, {"id": "940GZZLUEPG", "lat": 51.69368, "lon": 0.11377, "name": "Epping"}, {"id": "940GZZLUFLP", "lat": 51.59562, "lon": 0.091, "name": "Fairlop"}, {"id": "940GZZLUGFD", "lat": 51.54242, "lon": -0.34605, "name": "Greenford"}, {"id": "940GZZLUGGH", "lat": 51.61338, "lon": 0.09207, "name": "Grange Hill"}, {"id": "940GZZLUGTH", "lat": 51.57654, "lon": 0.06618, "name": "Gants Hill"}, {"id": "940GZZLUHBN", "lat": 51.51758, "lon": -0.12047, "name": "Holborn"}, {"id": "940GZZLUHGR", "lat": 51.53018, "lon": -0.2927, "name": "Hanger Lane"}, {"id": "940GZZLUHLT", "lat": 51.60366, "lon": 0.09348, "name": "Hainault"}, {"id": "940GZZLUHPK", "lat": 51.50714, "lon": -0.20568, "name": "Holland Park"}, {"id": "940GZZLULGN", "lat": 51.64144, "lon": 0.05548, "name": "Loughton"}, {"id": "940GZZLULGT", "lat": 51.51172, "lon": -0.17549, "name": "Lancaster Gate"}, {"id": "940GZZLULVT", "lat": 51.51737, "lon": -0.08318, "name": "Liverpool Street"}, {"id": "940GZZLULYN", "lat": 51.55659, "lon": -0.00552, "name": "Leyton"}, {"id": "940GZZLULYS", "lat": 51.56832, "lon": 0.00819, "name": "Leytonstone"}, {"id": "940GZZLUMBA", "lat": 51.51342, "lon": -0.15895, "name": "Marble Arch"}, {"id": "940GZZLUMED", "lat": 51.52512, "lon": -0.03364, "name": "Mile End"}, {"id": "940GZZLUNAN", "lat": 51.52352, "lon": -0.25976, "name": "North Acton"}, {"id": "940GZZLUNBP", "lat": 51.57573, "lon": 0.09, "name": "Newbury Park"}, {"id": "940GZZLUNHG", "lat": 51.50913, "lon": -0.1961, "name": "Notting Hill Gate"}, {"id": "940GZZLUNHT", "lat": 51.54824, "lon": -0.3687, "name": "Northolt"}, {"id": "940GZZLUPVL", "lat": 51.53672, "lon": -0.32345, "name": "Perivale"}, {"id": "940GZZLUQWY", "lat": 51.51031, "lon": -0.18715, "name": "Queensway"}, {"id": "940GZZLURBG", "lat": 51.57624, "lon": 0.04536, "name": "Redbridge"}, {"id": "940GZZLURSG", "lat": 51.56074, "lon": -0.41071, "name": "Ruislip Gardens"}, {"id": "940GZZLURVY", "lat": 51.6172, "lon": 0.04365, "name": "Roding Valley"}, {"id": "940GZZLUSBC", "lat": 51.50438, "lon": -0.21881, "name": "Shepherd's Bush (Central)"}, {"id": "940GZZLUSNB", "lat": 51.58068, "lon": 0.02144, "name": "Snaresbrook"}, {"id": "940GZZLUSPU", "lat": 51.51494, "lon": -0.09757, "name": "St. Paul's"}, {"id": "940GZZLUSRP", "lat": 51.55685, "lon": -0.39892, "name": "South Ruislip"}, {"id": "940GZZLUSTD", "lat": 51.54181, "lon": -0.00346, "name": "Stratford"}, {"id": "940GZZLUSWF", "lat": 51.59191, "lon": 0.02734, "name": "South Woodford"}, {"id": "940GZZLUTCR", "lat": 51.51643, "lon": -0.13041, "name": "Tottenham Court Road"}, {"id": "940GZZLUTHB", "lat": 51.67176, "lon": 0.10308, "name": "Theydon Bois"}, {"id": "940GZZLUWCY", "lat": 51.51196, "lon": -0.2243, "name": "White City"}, {"id": "940GZZLUWOF", "lat": 51.6069, "lon": 0.03397, "name": "Woodford"}, {"id": "940GZZLUWRP", "lat": 51.56969, "lon": -0.43789, "name": "West Ruislip"}, {"id": "940GZZLUWSD", "lat": 51.5755, "lon": 0.02853, "name": "Wanstead"}, {"id": "940GZZLUWTA", "lat": 51.518, "lon": -0.28098, "name": "West Acton"}, {"id": "940GZZLUALD", "lat": 51.51425, "lon": -0.07569, "name": "Aldgate"}, {"id": "940GZZLUBBN", "lat": 51.52027, "lon": -0.09799, "name": "Barbican"}, {"id": "940GZZLUBKF", "lat": 51.51158, "lon": -0.10366, "name": "Blackfriars"}, {"id": "940GZZLUBWT", "lat": 51.51228, "lon": -0.18794, "name": "Bayswater"}, {"id": "940GZZLUCST", "lat": 51.51151, "lon": -0.09043, "name": "Cannon Street"}, {"id": "940GZZLUERC", "lat": 51.51986, "lon": -0.16783, "name": "Edgware Road (Circle Line)"}, {"id": "940GZZLUESQ", "lat": 51.5256, "lon": -0.13583, "name": "Euston Square"}, {"id": "940GZZLUFCN", "lat": 51.52025, "lon": -0.10491, "name": "Farringdon"}, {"id": "940GZZLUGHK", "lat": 51.502, "lon": -0.22671, "name": "Goldhawk Road"}, {"id": "940GZZLUGPS", "lat": 51.52384, "lon": -0.14426, "name": "Great Portland Street"}, {"id": "940GZZLUGTR", "lat": 51.49432, "lon": -0.18266, "name": "Gloucester Road"}, {"id": "940GZZLUHSC", "lat": 51.49339, "lon": -0.22503, "name": "Hammersmith (H&C Line)"}, {"id": "940GZZLUHSK", "lat": 51.50106, "lon": -0.19279, "name": "High Street Kensington"}, {"id": "940GZZLUKSX", "lat": 51.53066, "lon": -0.12319, "name": "King's Cross St. Pancras"}, {"id": "940GZZLULAD", "lat": 51.51745, "lon": -0.21039, "name": "Ladbroke Grove"}, {"id": "940GZZLULRD", "lat": 51.51339, "lon": -0.2178, "name": "Latimer Road"}, {"id": "940GZZLUMGT", "lat": 51.51818, "lon": -0.08832, "name": "Moorgate"}, {"id": "940GZZLUMMT", "lat": 51.5107, "lon": -0.08597, "name": "Monument"}, {"id": "940GZZLUMSH", "lat": 51.51212, "lon": -0.09401, "name": "Mansion House"}, {"id": "940GZZLUPAH", "lat": 51.51819, "lon": -0.17831, "name": "Paddington (H&C Line)-Underground"}, {"id": "940GZZLURYO", "lat": 51.51911, "lon": -0.18875, "name": "Royal Oak"}, {"id": "940GZZLUSBM", "lat": 51.50558, "lon": -0.22637, "name": "Shepherd's Bush Market"}, {"id": "940GZZLUSJP", "lat": 51.49954, "lon": -0.13361, "name": "St. James's Park"}, {"id": "940GZZLUSKS", "lat": 51.49409, "lon": -0.17414, "name": "South Kensington"}, {"id": "940GZZLUSSQ", "lat": 51.49227, "lon": -0.15638, "name": "Sloane Square"}, {"id": "940GZZLUTMP", "lat": 51.51101, "lon": -0.11426, "name": "Temple"}, {"id": "940GZZLUTWH", "lat": 51.50997, "lon": -0.07655, "name": "Tower Hill"}, {"id": "940GZZLUVIC", "lat": 51.49636, "lon": -0.1431, "name": "Victoria"}, {"id": "940GZZLUWLA", "lat": 51.50967, "lon": -0.22453, "name": "Wood Lane"}, {"id": "940GZZLUWSM", "lat": 51.50132, "lon": -0.12486, "name": "Westminster"}, {"id": "940GZZLUWSP", "lat": 51.52111, "lon": -0.20106, "name": "Westbourne Park"}, {"id": "940GZZLUACT", "lat": 51.50306, "lon": -0.28046, "name": "Acton Town"}, {"id": "940GZZLUADE", "lat": 51.51504, "lon": -0.07238, "name": "Aldgate East"}, {"id": "940GZZLUBBB", "lat": 51.52484, "lon": -0.01154, "name": "Bromley-by-Bow"}, {"id": "940GZZLUBEC", "lat": 51.54033, "lon": 0.12702, "name": "Becontree"}, {"id": "940GZZLUBKG", "lat": 51.53932, "lon": 0.08105, "name": "Barking"}, {"id": "940GZZLUBSC", "lat": 51.49031, "lon": -0.21343, "name": "Barons Court"}, {"id": "940GZZLUBWR", "lat": 51.52694, "lon": -0.02513, "name": "Bow Road"}, {"id": "940GZZLUCWP", "lat": 51.49463, "lon": -0.26797, "name": "Chiswick Park"}, {"id": "940GZZLUDGE", "lat": 51.5441, "lon": 0.16602, "name": "Dagenham East"}, {"id": "940GZZLUDGY", "lat": 51.54164, "lon": 0.14753, "name": "Dagenham Heathway"}, {"id": "940GZZLUECM", "lat": 51.51014, "lon": -0.28826, "name": "Ealing Common"}, {"id": "940GZZLUECT", "lat": 51.49206, "lon": -0.19338, "name": "Earl's Court"}, {"id": "940GZZLUEHM", "lat": 51.53895, "lon": 0.05119, "name": "East Ham"}, {"id": "940GZZLUEPK", "lat": 51.54977, "lon": 0.19864, "name": "Elm Park"}, {"id": "940GZZLUEPY", "lat": 51.4592, "lon": -0.211, "name": "East Putney"}, {"id": "940GZZLUFBY", "lat": 51.48008, "lon": -0.19542, "name": "Fulham Broadway"}, {"id": "940GZZLUGBY", "lat": 51.4918, "lon": -0.27527, "name": "Gunnersbury"}, {"id": "940GZZLUHCH", "lat": 51.55409, "lon": 0.21912, "name": "Hornchurch"}, {"id": "940GZZLUHSD", "lat": 51.4923, "lon": -0.22362, "name": "Hammersmith (Dist&Picc Line)"}, {"id": "940GZZLUKOY", "lat": 51.49762, "lon": -0.21002, "name": "Kensington (Olympia)"}, {"id": "940GZZLUKWG", "lat": 51.47706, "lon": -0.28524, "name": "Kew Gardens"}, {"id": "940GZZLUPLW", "lat": 51.53134, "lon": 0.01745, "name": "Plaistow"}, {"id": "940GZZLUPSG", "lat": 51.47528, "lon": -0.20117, "name": "Parsons Green"}, {"id": "940GZZLUPYB", "lat": 51.46826, "lon": -0.20873, "name": "Putney Bridge"}, {"id": "940GZZLURMD", "lat": 51.46324, "lon": -0.30134, "name": "Richmond"}, {"id": "940GZZLURVP", "lat": 51.49412, "lon": -0.23588, "name": "Ravenscourt Park"}, {"id": "940GZZLUSFB", "lat": 51.49492, "lon": -0.2457, "name": "Stamford Brook"}, {"id": "940GZZLUSFS", "lat": 51.44507, "lon": -0.2066, "name": "Southfields"}, {"id": "940GZZLUSGN", "lat": 51.52186, "lon": -0.0466, "name": "Stepney Green"}, {"id": "940GZZLUTNG", "lat": 51.49515, "lon": -0.25455, "name": "Turnham Green"}, {"id": "940GZZLUUPB", "lat": 51.55856, "lon": 0.23581, "name": "Upminster Bridge"}, {"id": "940GZZLUUPK", "lat": 51.53534, "lon": 0.03526, "name": "Upton Park"}, {"id": "940GZZLUUPM", "lat": 51.55906, "lon": 0.25088, "name": "Upminster"}, {"id": "940GZZLUUPY", "lat": 51.53837, "lon": 0.10153, "name": "Upney"}, {"id": "940GZZLUWBN", "lat": 51.48727, "lon": -0.1956, "name": "West Brompton"}, {"id": "940GZZLUWHM", "lat": 51.52814, "lon": 0.00505, "name": "West Ham"}, {"id": "940GZZLUWIM", "lat": 51.42121, "lon": -0.20657, "name": "Wimbledon"}, {"id": "940GZZLUWIP", "lat": 51.43457, "lon": -0.19972, "name": "Wimbledon Park"}, {"id": "940GZZLUWKN", "lat": 51.49046, "lon": -0.20664, "name": "West Kensington"}, {"id": "940GZZLUWPL", "lat": 51.51952, "lon": -0.05997, "name": "Whitechapel"}, {"id": "940GZZLUBMY", "lat": 51.49775, "lon": -0.06399, "name": "Bermondsey"}, {"id": "940GZZLUCGT", "lat": 51.51358, "lon": 0.00832, "name": "Canning Town"}, {"id": "940GZZLUCPK", "lat": 51.6077, "lon": -0.29469, "name": "Canons Park"}, {"id": "940GZZLUCWR", "lat": 51.49793, "lon": -0.0494, "name": "Canada Water"}, {"id": "940GZZLUCYF", "lat": 51.50349, "lon": -0.01825, "name": "Canary Wharf"}, {"id": "940GZZLUDOH", "lat": 51.55195, "lon": -0.23907, "name": "Dollis Hill"}, {"id": "940GZZLUFYR", "lat": 51.54682, "lon": -0.17985, "name": "Finchley Road"}, {"id": "940GZZLUGPK", "lat": 51.50695, "lon": -0.14279, "name": "Green Park"}, {"id": "940GZZLUKBN", "lat": 51.54718, "lon": -0.20425, "name": "Kilburn"}, {"id": "940GZZLUKBY", "lat": 51.58485, "lon": -0.27879, "name": "Kingsbury"}, {"id": "940GZZLULNB", "lat": 51.50572, "lon": -0.08887, "name": "London Bridge"}, {"id": "940GZZLUNDN", "lat": 51.55399, "lon": -0.24984, "name": "Neasden"}, {"id": "940GZZLUNGW", "lat": 51.50047, "lon": 0.00429, "name": "North Greenwich"}, {"id": "940GZZLUQBY", "lat": 51.59419, "lon": -0.28622, "name": "Queensbury"}, {"id": "940GZZLUSJW", "lat": 51.53452, "lon": -0.17395, "name": "St. John's Wood"}, {"id": "940GZZLUSTM", "lat": 51.61984, "lon": -0.30327, "name": "Stanmore"}, {"id": "940GZZLUSWC", "lat": 51.54368, "lon": -0.17489, "name": "Swiss Cottage"}, {"id": "940GZZLUSWK", "lat": 51.50427, "lon": -0.10533, "name": "Southwark"}, {"id": "940GZZLUWHP", "lat": 51.54664, "lon": -0.19106, "name": "West Hampstead"}, {"id": "940GZZLUWIG", "lat": 51.54915, "lon": -0.22154, "name": "Willesden Green"}, {"id": "940GZZLUWYP", "lat": 51.5632, "lon": -0.27926, "name": "Wembley Park"}, {"id": "940GZZLUAMS", "lat": 51.67413, "lon": -0.60771, "name": "Amersham"}, {"id": "940GZZLUCAL", "lat": 51.66799, "lon": -0.56069, "name": "Chalfont & Latimer"}, {"id": "940GZZLUCSM", "lat": 51.70521, "lon": -0.61125, "name": "Chesham"}, {"id": "940GZZLUCXY", "lat": 51.64704, "lon": -0.44172, "name": "Croxley"}, {"id": "940GZZLUCYD", "lat": 51.65436, "lon": -0.51846, "name": "Chorleywood"}, {"id": "940GZZLUEAE", "lat": 51.57651, "lon": -0.39737, "name": "Eastcote"}, {"id": "940GZZLUHGD", "lat": 51.55371, "lon": -0.44983, "name": "Hillingdon"}, {"id": "940GZZLUHOH", "lat": 51.57919, "lon": -0.33722, "name": "Harrow-on-the-Hill"}, {"id": "940GZZLUICK", "lat": 51.56199, "lon": -0.442, "name": "Ickenham"}, {"id": "940GZZLUMPK", "lat": 51.62985, "lon": -0.43245, "name": "Moor Park"}, {"id": "940GZZLUNHA", "lat": 51.58487, "lon": -0.36241, "name": "North Harrow"}, {"id": "940GZZLUNKP", "lat": 51.57848, "lon": -0.31806, "name": "Northwick Park"}, {"id": "940GZZLUNOW", "lat": 51.61105, "lon": -0.42383, "name": "Northwood"}, {"id": "940GZZLUNWH", "lat": 51.60057, "lon": -0.40946, "name": "Northwood Hills"}, {"id": "940GZZLUPNR", "lat": 51.5929, "lon": -0.38116, "name": "Pinner"}, {"id": "940GZZLUPRD", "lat": 51.57197, "lon": -0.29511, "name": "Preston Road"}, {"id": "940GZZLURKW", "lat": 51.64021, "lon": -0.4737, "name": "Rickmansworth"}, {"id": "940GZZLURSM", "lat": 51.5732, "lon": -0.41297, "name": "Ruislip Manor"}, {"id": "940GZZLURSP", "lat": 51.57135, "lon": -0.4219, "name": "Ruislip"}, {"id": "940GZZLURYL", "lat": 51.57515, "lon": -0.37113, "name": "Rayners Lane"}, {"id": "940GZZLUUXB", "lat": 51.54657, "lon": -0.47795, "name": "Uxbridge"}, {"id": "940GZZLUWAF", "lat": 51.65745, "lon": -0.41738, "name": "Watford"}, {"id": "940GZZLUWHW", "lat": 51.57971, "lon": -0.3534, "name": "West Harrow"}, {"id": "940GZZBPSUST", "lat": 51.47993, "lon": -0.14214, "name": "Battersea Power Station"}, {"id": "940GZZLUACY", "lat": 51.56548, "lon": -0.13482, "name": "Archway"}, {"id": "940GZZLUAGL", "lat": 51.53262, "lon": -0.1059, "name": "Angel"}, {"id": "940GZZLUBLM", "lat": 51.44329, "lon": -0.153, "name": "Balham"}, {"id": "940GZZLUBOR", "lat": 51.5012, "lon": -0.09337, "name": "Borough"}, {"id": "940GZZLUBTK", "lat": 51.60277, "lon": -0.26405, "name": "Burnt Oak"}, {"id": "940GZZLUBTX", "lat": 51.57665, "lon": -0.21362, "name": "Brent Cross"}, {"id": "940GZZLUBZP", "lat": 51.55053, "lon": -0.16478, "name": "Belsize Park"}, {"id": "940GZZLUCFM", "lat": 51.54412, "lon": -0.15339, "name": "Chalk Farm"}, {"id": "940GZZLUCND", "lat": 51.59542, "lon": -0.24992, "name": "Colindale"}, {"id": "940GZZLUCPC", "lat": 51.46174, "lon": -0.13832, "name": "Clapham Common"}, {"id": "940GZZLUCPN", "lat": 51.46513, "lon": -0.13002, "name": "Clapham North"}, {"id": "940GZZLUCPS", "lat": 51.45265, "lon": -0.14758, "name": "Clapham South"}, {"id": "940GZZLUCSD", "lat": 51.41816, "lon": -0.17809, "name": "Colliers Wood"}, {"id": "940GZZLUCTN", "lat": 51.53929, "lon": -0.14274, "name": "Camden Town"}, {"id": "940GZZLUEFY", "lat": 51.58713, "lon": -0.16501, "name": "East Finchley"}, {"id": "940GZZLUEGW", "lat": 51.61365, "lon": -0.27493, "name": "Edgware"}, {"id": "940GZZLUEUS", "lat": 51.52806, "lon": -0.13218, "name": "Euston"}, {"id": "940GZZLUFYC", "lat": 51.60092, "lon": -0.19253, "name": "Finchley Central"}, {"id": "940GZZLUGDG", "lat": 51.5206, "lon": -0.13436, "name": "Goodge Street"}, {"id": "940GZZLUGGN", "lat": 51.57226, "lon": -0.19404, "name": "Golders Green"}, {"id": "940GZZLUHBT", "lat": 51.65054, "lon": -0.1943, "name": "High Barnet"}, {"id": "940GZZLUHCL", "lat": 51.5833, "lon": -0.22642, "name": "Hendon Central"}, {"id": "940GZZLUHGT", "lat": 51.57753, "lon": -0.14586, "name": "Highgate"}, {"id": "940GZZLUHTD", "lat": 51.55624, "lon": -0.17746, "name": "Hampstead"}, {"id": "940GZZLUKNG", "lat": 51.48834, "lon": -0.10596, "name": "Kennington"}, {"id": "940GZZLUKSH", "lat": 51.55031, "lon": -0.14073, "name": "Kentish Town"}, {"id": "940GZZLULSQ", "lat": 51.51139, "lon": -0.12843, "name": "Leicester Square"}, {"id": "940GZZLUMDN", "lat": 51.40214, "lon": -0.19484, "name": "Morden"}, {"id": "940GZZLUMHL", "lat": 51.60823, "lon": -0.20999, "name": "Mill Hill East"}, {"id": "940GZZLUMTC", "lat": 51.53468, "lon": -0.13879, "name": "Mornington Crescent"}, {"id": "940GZZLUODS", "lat": 51.52586, "lon": -0.08777, "name": "Old Street"}, {"id": "940GZZLUOVL", "lat": 51.48185, "lon": -0.11244, "name": "Oval"}, {"id": "940GZZLUSKW", "lat": 51.47218, "lon": -0.12264, "name": "Stockwell"}, {"id": "940GZZLUSWN", "lat": 51.41531, "lon": -0.19201, "name": "South Wimbledon"}, {"id": "940GZZLUTAW", "lat": 51.6306, "lon": -0.17921, "name": "Totteridge & Whetstone"}, {"id": "940GZZLUTBC", "lat": 51.43568, "lon": -0.15974, "name": "Tooting Bec"}, {"id": "940GZZLUTBY", "lat": 51.42763, "lon": -0.16837, "name": "Tooting Broadway"}, {"id": "940GZZLUTFP", "lat": 51.55682, "lon": -0.13843, "name": "Tufnell Park"}, {"id": "940GZZLUWFN", "lat": 51.60943, "lon": -0.18836, "name": "West Finchley"}, {"id": "940GZZLUWOP", "lat": 51.61801, "lon": -0.18542, "name": "Woodside Park"}, {"id": "940GZZLUWRR", "lat": 51.52495, "lon": -0.13832, "name": "Warren Street"}, {"id": "940GZZNEUGST", "lat": 51.47991, "lon": -0.12848, "name": "Nine Elms"}, {"id": "940GZZLUALP", "lat": 51.54063, "lon": -0.29961, "name": "Alperton"}, {"id": "940GZZLUASG", "lat": 51.61645, "lon": -0.13306, "name": "Arnos Grove"}, {"id": "940GZZLUASL", "lat": 51.55866, "lon": -0.10746, "name": "Arsenal"}, {"id": "940GZZLUBDS", "lat": 51.60703, "lon": -0.12423, "name": "Bounds Green"}, {"id": "940GZZLUBOS", "lat": 51.49564, "lon": -0.32494, "name": "Boston Manor"}, {"id": "940GZZLUCAR", "lat": 51.54852, "lon": -0.11849, "name": "Caledonian Road"}, {"id": "940GZZLUCGN", "lat": 51.51309, "lon": -0.12444, "name": "Covent Garden"}, {"id": "940GZZLUCKS", "lat": 51.65152, "lon": -0.14917, "name": "Cockfosters"}, {"id": "940GZZLUFPK", "lat": 51.56416, "lon": -0.10683, "name": "Finsbury Park"}, {"id": "940GZZLUHNX", "lat": 51.46675, "lon": -0.42319, "name": "Hatton Cross"}, {"id": "940GZZLUHPC", "lat": 51.50303, "lon": -0.15244, "name": "Hyde Park Corner"}, {"id": "940GZZLUHR4", "lat": 51.45852, "lon": -0.44577, "name": "Heathrow Terminal 4"}, {"id": "940GZZLUHR5", "lat": 51.47005, "lon": -0.49056, "name": "Heathrow Terminal 5"}, {"id": "940GZZLUHRC", "lat": 51.47124, "lon": -0.45226, "name": "Heathrow Terminals 2 & 3"}, {"id": "940GZZLUHWC", "lat": 51.47129, "lon": -0.36658, "name": "Hounslow Central"}, {"id": "940GZZLUHWE", "lat": 51.47321, "lon": -0.35647, "name": "Hounslow East"}, {"id": "940GZZLUHWT", "lat": 51.47347, "lon": -0.38654, "name": "Hounslow West"}, {"id": "940GZZLUHWY", "lat": 51.5527, "lon": -0.11324, "name": "Holloway Road"}, {"id": "940GZZLUKNB", "lat": 51.50167, "lon": -0.16051, "name": "Knightsbridge"}, {"id": "940GZZLUMRH", "lat": 51.57074, "lon": -0.09612, "name": "Manor House"}, {"id": "940GZZLUNEN", "lat": 51.5175, "lon": -0.28887, "name": "North Ealing"}, {"id": "940GZZLUNFD", "lat": 51.49932, "lon": -0.31472, "name": "Northfields"}, {"id": "940GZZLUOAK", "lat": 51.64773, "lon": -0.13218, "name": "Oakwood"}, {"id": "940GZZLUOSY", "lat": 51.48127, "lon": -0.35222, "name": "Osterley"}, {"id": "940GZZLUPKR", "lat": 51.52712, "lon": -0.28434, "name": "Park Royal"}, {"id": "940GZZLURSQ", "lat": 51.52307, "lon": -0.12429, "name": "Russell Square"}, {"id": "940GZZLUSEA", "lat": 51.501, "lon": -0.30742, "name": "South Ealing"}, {"id": "940GZZLUSGT", "lat": 51.63231, "lon": -0.12782, "name": "Southgate"}, {"id": "940GZZLUSHH", "lat": 51.56489, "lon": -0.35249, "name": "South Harrow"}, {"id": "940GZZLUSUH", "lat": 51.55695, "lon": -0.33643, "name": "Sudbury Hill"}, {"id": "940GZZLUSUT", "lat": 51.55082, "lon": -0.31574, "name": "Sudbury Town"}, {"id": "940GZZLUTPN", "lat": 51.59027, "lon": -0.10295, "name": "Turnpike Lane"}, {"id": "940GZZLUWOG", "lat": 51.59748, "lon": -0.10989, "name": "Wood Green"}, {"id": "940GZZLUBLR", "lat": 51.58692, "lon": -0.04115, "name": "Blackhorse Road"}, {"id": "940GZZLUBXN", "lat": 51.46262, "lon": -0.11489, "name": "Brixton"}, {"id": "940GZZLUHAI", "lat": 51.54635, "lon": -0.10332, "name": "Highbury & Islington"}, {"id": "940GZZLUPCO", "lat": 51.4891, "lon": -0.13376, "name": "Pimlico"}, {"id": "940GZZLUSVS", "lat": 51.58333, "lon": -0.07258, "name": "Seven Sisters"}, {"id": "940GZZLUTMH", "lat": 51.58811, "lon": -0.06024, "name": "Tottenham Hale"}, {"id": "940GZZLUVXL", "lat": 51.48574, "lon": -0.1242, "name": "Vauxhall"}, {"id": "940GZZLUWWL", "lat": 51.58297, "lon": -0.01988, "name": "Walthamstow Central"}, {"id": "940GZZDLABR", "lat": 51.53193, "lon": 0.00374, "name": "Abbey Road"}, {"id": "940GZZDLALL", "lat": 51.511, "lon": -0.01314, "name": "All Saints"}, {"id": "940GZZDLBEC", "lat": 51.51436, "lon": 0.06145, "name": "Beckton"}, {"id": "940GZZDLBLA", "lat": 51.50799, "lon": -0.00697, "name": "Blackwall"}, {"id": "940GZZDLBNK", "lat": 51.51323, "lon": -0.08851, "name": "Bank"}, {"id": "940GZZDLBOW", "lat": 51.52786, "lon": -0.02094, "name": "Bow Church"}, {"id": "940GZZDLBPK", "lat": 51.50879, "lon": 0.05493, "name": "Beckton Park"}, {"id": "940GZZDLCAN", "lat": 51.50484, "lon": -0.021, "name": "Canary Wharf"}, {"id": "940GZZDLCGT", "lat": 51.51413, "lon": 0.0081, "name": "Canning Town"}, {"id": "940GZZDLCLA", "lat": 51.49573, "lon": -0.01461, "name": "Crossharbour"}, {"id": "940GZZDLCUS", "lat": 51.50972, "lon": 0.0267, "name": "Custom House (for ExCel)"}, {"id": "940GZZDLCUT", "lat": 51.48167, "lon": -0.01081, "name": "Cutty Sark (for Maritime Greenwich)"}, {"id": "940GZZDLCYP", "lat": 51.50847, "lon": 0.06392, "name": "Cyprus"}, {"id": "940GZZDLDEP", "lat": 51.47422, "lon": -0.02244, "name": "Deptford Bridge"}, {"id": "940GZZDLDEV", "lat": 51.52267, "lon": -0.01761, "name": "Devons Road"}, {"id": "940GZZDLEIN", "lat": 51.50936, "lon": -0.00233, "name": "East India"}, {"id": "940GZZDLELV", "lat": 51.46907, "lon": -0.01673, "name": "Elverson Road"}, {"id": "940GZZDLGAL", "lat": 51.50894, "lon": 0.07155, "name": "Gallions Reach"}, {"id": "940GZZDLGRE", "lat": 51.47809, "lon": -0.01367, "name": "Greenwich"}, {"id": "940GZZDLHEQ", "lat": 51.50338, "lon": -0.02142, "name": "Heron Quays"}, {"id": "940GZZDLISL", "lat": 51.48781, "lon": -0.01014, "name": "Island Gardens"}, {"id": "940GZZDLKGV", "lat": 51.502, "lon": 0.06262, "name": "King George V"}, {"id": "940GZZDLLCA", "lat": 51.50342, "lon": 0.04874, "name": "London City Airport"}, {"id": "940GZZDLLDP", "lat": 51.51517, "lon": -0.01415, "name": "Langdon Park"}, {"id": "940GZZDLLEW", "lat": 51.46466, "lon": -0.01287, "name": "Lewisham"}, {"id": "940GZZDLLIM", "lat": 51.51239, "lon": -0.03981, "name": "Limehouse"}, {"id": "940GZZDLMUD", "lat": 51.4907, "lon": -0.01474, "name": "Mudchute"}, {"id": "940GZZDLPDK", "lat": 51.50221, "lon": 0.03211, "name": "Pontoon Dock"}, {"id": "940GZZDLPOP", "lat": 51.50774, "lon": -0.01738, "name": "Poplar"}, {"id": "940GZZDLPRE", "lat": 51.50926, "lon": 0.03416, "name": "Prince Regent"}, {"id": "940GZZDLPUD", "lat": 51.5343, "lon": -0.01276, "name": "Pudding Mill Lane"}, {"id": "940GZZDLRAL", "lat": 51.50836, "lon": 0.04593, "name": "Royal Albert"}, {"id": "940GZZDLRVC", "lat": 51.50934, "lon": 0.0185, "name": "Royal Victoria"}, {"id": "940GZZDLSHA", "lat": 51.51169, "lon": -0.05664, "name": "Shadwell"}, {"id": "940GZZDLSHS", "lat": 51.5382, "lon": -0.00108, "name": "Stratford High Street"}, {"id": "940GZZDLSIT", "lat": 51.54527, "lon": -0.00964, "name": "Stratford International"}, {"id": "940GZZDLSOQ", "lat": 51.50005, "lon": -0.01597, "name": "South Quay"}, {"id": "940GZZDLSTD", "lat": 51.54176, "lon": -0.00329, "name": "Stratford"}, {"id": "940GZZDLSTL", "lat": 51.52079, "lon": 0.00416, "name": "Star Lane"}, {"id": "940GZZDLTWG", "lat": 51.51062, "lon": -0.07482, "name": "Tower Gateway"}, {"id": "940GZZDLWFE", "lat": 51.50943, "lon": -0.02675, "name": "Westferry"}, {"id": "940GZZDLWHM", "lat": 51.52789, "lon": 0.00448, "name": "West Ham"}, {"id": "940GZZDLWIQ", "lat": 51.50703, "lon": -0.02031, "name": "West India Quay"}, {"id": "940GZZDLWLA", "lat": 51.49001, "lon": 0.06913, "name": "Woolwich Arsenal"}, {"id": "940GZZDLWSV", "lat": 51.50284, "lon": 0.02246, "name": "West Silvertown"}, {"id": "910GEMRSPKH", "lat": 51.56864, "lon": 0.22011, "name": "Emerson Park"}, {"id": "910GROMFORD", "lat": 51.57483, "lon": 0.18324, "name": "Romford"}, {"id": "910GUPMNSTR", "lat": 51.55902, "lon": 0.25088, "name": "Upminster"}, {"id": "910GBUSHYDC", "lat": 51.64569, "lon": -0.38561, "name": "Bushey"}, {"id": "910GCRPNDPK", "lat": 51.62835, "lon": -0.38594, "name": "Carpenders Park"}, {"id": "910GEUSTON", "lat": 51.52814, "lon": -0.13392, "name": "London Euston"}, {"id": "910GHARLSDN", "lat": 51.53629, "lon": -0.25767, "name": "Harlesden"}, {"id": "910GHEDSTNL", "lat": 51.60265, "lon": -0.35722, "name": "Headstone Lane"}, {"id": "910GHROW", "lat": 51.59217, "lon": -0.33457, "name": "Harrow & Wealdstone"}, {"id": "910GHTCHEND", "lat": 51.60942, "lon": -0.3686, "name": "Hatch End"}, {"id": "910GKENSLG", "lat": 51.53054, "lon": -0.22509, "name": "Kensal Green"}, {"id": "910GKLBRNHR", "lat": 51.53728, "lon": -0.19224, "name": "Kilburn High Road"}, {"id": "910GKTON", "lat": 51.5818, "lon": -0.31698, "name": "Kenton"}, {"id": "910GNWEMBLY", "lat": 51.5626, "lon": -0.30398, "name": "North Wembley"}, {"id": "910GQPRK", "lat": 51.53397, "lon": -0.20499, "name": "Queens Park (London)"}, {"id": "910GSHMPSTD", "lat": 51.54143, "lon": -0.17888, "name": "South Hampstead"}, {"id": "910GSKENTON", "lat": 51.57021, "lon": -0.30846, "name": "South Kenton"}, {"id": "910GSTNBGPK", "lat": 51.54411, "lon": -0.27583, "name": "Stonebridge Park"}, {"id": "910GWATFDHS", "lat": 51.65266, "lon": -0.39171, "name": "Watford High Street"}, {"id": "910GWATFJDC", "lat": 51.66353, "lon": -0.39652, "name": "Watford Junction"}, {"id": "910GWLSDJHL", "lat": 51.5325, "lon": -0.24455, "name": "Willesden Junction"}, {"id": "910GWMBY", "lat": 51.55233, "lon": -0.29643, "name": "Wembley Central"}, {"id": "910GACTNCTL", "lat": 51.50872, "lon": -0.26297, "name": "Acton Central"}, {"id": "910GBRBY", "lat": 51.54517, "lon": -0.20231, "name": "Brondesbury"}, {"id": "910GBRBYPK", "lat": 51.54073, "lon": -0.21005, "name": "Brondesbury Park"}, {"id": "910GCLDNNRB", "lat": 51.54304, "lon": -0.11673, "name": "Caledonian Road & Barnsbury"}, {"id": "910GCLPHMJ1", "lat": 51.46419, "lon": -0.17022, "name": "Clapham Junction"}, {"id": "910GCLPHMJC", "lat": 51.46419, "lon": -0.17029, "name": "Clapham Junction"}, {"id": "910GCMDNRD", "lat": 51.54179, "lon": -0.1387, "name": "Camden Road"}, {"id": "910GCNNB", "lat": 51.54873, "lon": -0.09219, "name": "Canonbury"}, {"id": "910GCSEAH", "lat": 51.47495, "lon": -0.18282, "name": "Imperial Wharf"}, {"id": "910GDALSKLD", "lat": 51.54815, "lon": -0.0757, "name": "Dalston Kingsland"}, {"id": "910GFNCHLYR", "lat": 51.55027, "lon": -0.18314, "name": "Finchley Road & Frognal"}, {"id": "910GGNRSBRY", "lat": 51.49168, "lon": -0.27529, "name": "Gunnersbury"}, {"id": "910GGOSPLOK", "lat": 51.55533, "lon": -0.15077, "name": "Gospel Oak"}, {"id": "910GHACKNYC", "lat": 51.54711, "lon": -0.05606, "name": "Hackney Central"}, {"id": "910GHACKNYW", "lat": 51.54341, "lon": -0.02492, "name": "Hackney Wick"}, {"id": "910GHGHI", "lat": 51.54618, "lon": -0.10376, "name": "Highbury & Islington"}, {"id": "910GHMPSTDH", "lat": 51.55521, "lon": -0.1657, "name": "Hampstead Heath"}, {"id": "910GHOMRTON", "lat": 51.54701, "lon": -0.04236, "name": "Homerton"}, {"id": "910GKENOLYM", "lat": 51.4979, "lon": -0.21036, "name": "Kensington (Olympia)"}, {"id": "910GKENR", "lat": 51.53455, "lon": -0.21996, "name": "Kensal Rise"}, {"id": "910GKEWGRDN", "lat": 51.47707, "lon": -0.28505, "name": "Kew Gardens"}, {"id": "910GKNTSHTW", "lat": 51.54655, "lon": -0.14666, "name": "Kentish Town West"}, {"id": "910GRICHMND", "lat": 51.46306, "lon": -0.30156, "name": "Richmond (London)"}, {"id": "910GSACTON", "lat": 51.4997, "lon": -0.27016, "name": "South Acton"}, {"id": "910GSHPDSB", "lat": 51.50529, "lon": -0.21765, "name": "Shepherds Bush"}, {"id": "910GSTFD", "lat": 51.54189, "lon": -0.0034, "name": "Stratford (London)"}, {"id": "910GWBRMPTN", "lat": 51.48706, "lon": -0.19559, "name": "West Brompton"}, {"id": "910GWHMDSTD", "lat": 51.54747, "lon": -0.19118, "name": "West Hampstead"}, {"id": "910GBARKING", "lat": 51.5395, "lon": 0.0809, "name": "Barking"}, {"id": "910GBKRVS", "lat": 51.51953, "lon": 0.11596, "name": "Barking Riverside"}, {"id": "910GBLCHSRD", "lat": 51.5866, "lon": -0.04124, "name": "Blackhorse Road"}, {"id": "910GCROUCHH", "lat": 51.5713, "lon": -0.11715, "name": "Crouch Hill"}, {"id": "910GHRGYGL", "lat": 51.57718, "lon": -0.09814, "name": "Harringay Green Lanes"}, {"id": "910GLEYTNMR", "lat": 51.56972, "lon": -0.00805, "name": "Leyton Midland Road"}, {"id": "910GLYTNSHR", "lat": 51.56355, "lon": 0.00842, "name": "Leytonstone High Road"}, {"id": "910GSTOTNHM", "lat": 51.58037, "lon": -0.0721, "name": "South Tottenham"}, {"id": "910GUPRHLWY", "lat": 51.56363, "lon": -0.12951, "name": "Upper Holloway"}, {"id": "910GWDGRNPK", "lat": 51.54926, "lon": 0.04442, "name": "Woodgrange Park"}, {"id": "910GWLTHQRD", "lat": 51.5815, "lon": -0.02385, "name": "Walthamstow Queens Road"}, {"id": "910GWNSTDPK", "lat": 51.55169, "lon": 0.02621, "name": "Wanstead Park"}, {"id": "910GBHILLPK", "lat": 51.64152, "lon": -0.06922, "name": "Bush Hill Park"}, {"id": "910GBRUCGRV", "lat": 51.59396, "lon": -0.06987, "name": "Bruce Grove"}, {"id": "910GBTHNLGR", "lat": 51.52392, "lon": -0.05957, "name": "Bethnal Green"}, {"id": "910GCAMHTH", "lat": 51.53197, "lon": -0.05728, "name": "Cambridge Heath (London)"}, {"id": "910GCHESHNT", "lat": 51.70288, "lon": -0.02396, "name": "Cheshunt"}, {"id": "910GCHINGFD", "lat": 51.63309, "lon": 0.0099, "name": "Chingford"}, {"id": "910GCLAPTON", "lat": 51.56164, "lon": -0.05702, "name": "Clapton"}, {"id": "910GEDMNGRN", "lat": 51.62493, "lon": -0.06111, "name": "Edmonton Green"}, {"id": "910GENFLDTN", "lat": 51.65203, "lon": -0.07933, "name": "Enfield Town"}, {"id": "910GHAKNYNM", "lat": 51.54876, "lon": -0.06082, "name": "Hackney Downs"}, {"id": "910GHGHMSPK", "lat": 51.60835, "lon": -0.00022, "name": "Highams Park"}, {"id": "910GLIVST", "lat": 51.51799, "lon": -0.08143, "name": "London Liverpool Street"}, {"id": "910GLONFLDS", "lat": 51.54115, "lon": -0.05775, "name": "London Fields"}, {"id": "910GRCTRYRD", "lat": 51.5585, "lon": -0.06827, "name": "Rectory Road"}, {"id": "910GSBURY", "lat": 51.6487, "lon": -0.05244, "name": "Southbury"}, {"id": "910GSEVNSIS", "lat": 51.58227, "lon": -0.07527, "name": "Seven Sisters"}, {"id": "910GSIVRST", "lat": 51.61469, "lon": -0.06724, "name": "Silver Street"}, {"id": "910GSTJMSST", "lat": 51.58098, "lon": -0.03292, "name": "St James Street (London)"}, {"id": "910GSTKNWNG", "lat": 51.56523, "lon": -0.07289, "name": "Stoke Newington"}, {"id": "910GSTMFDHL", "lat": 51.57447, "lon": -0.07668, "name": "Stamford Hill"}, {"id": "910GTHBLDSG", "lat": 51.69246, "lon": -0.03483, "name": "Theobalds Grove"}, {"id": "910GTURKYST", "lat": 51.67263, "lon": -0.04722, "name": "Turkey Street"}, {"id": "910GWDST", "lat": 51.58658, "lon": -0.00241, "name": "Wood Street"}, {"id": "910GWHHRTLA", "lat": 51.60504, "lon": -0.07091, "name": "White Hart Lane"}, {"id": "910GWLTWCEN", "lat": 51.58292, "lon": -0.01981, "name": "Walthamstow Central"}, {"id": "910GANERLEY", "lat": 51.41215, "lon": -0.06589, "name": "Anerley"}, {"id": "910GBROCKLY", "lat": 51.46465, "lon": -0.03754, "name": "Brockley"}, {"id": "910GCLPHHS", "lat": 51.46548, "lon": -0.13252, "name": "Clapham High Street"}, {"id": "910GCNDAW", "lat": 51.49799, "lon": -0.04972, "name": "Canada Water"}, {"id": "910GCRYSTLP", "lat": 51.41811, "lon": -0.07261, "name": "Crystal Palace"}, {"id": "910GDALS", "lat": 51.54612, "lon": -0.07514, "name": "Dalston Junction"}, {"id": "910GDENMRKH", "lat": 51.4682, "lon": -0.08936, "name": "Denmark Hill"}, {"id": "910GFORESTH", "lat": 51.43928, "lon": -0.05316, "name": "Forest Hill"}, {"id": "910GHAGGERS", "lat": 51.53871, "lon": -0.07567, "name": "Haggerston"}, {"id": "910GHONROPK", "lat": 51.44999, "lon": -0.0455, "name": "Honor Oak Park"}, {"id": "910GHOXTON", "lat": 51.53151, "lon": -0.07568, "name": "Hoxton"}, {"id": "910GNEWXGTE", "lat": 51.47513, "lon": -0.0404, "name": "New Cross Gate"}, {"id": "910GNORWDJ", "lat": 51.39702, "lon": -0.07522, "name": "Norwood Junction"}, {"id": "910GNWCRELL", "lat": 51.47634, "lon": -0.03244, "name": "New Cross ELL"}, {"id": "910GPCKHMQD", "lat": 51.47357, "lon": -0.05731, "name": "Queens Road Peckham"}, {"id": "910GPCKHMRY", "lat": 51.47003, "lon": -0.06941, "name": "Peckham Rye"}, {"id": "910GPENEW", "lat": 51.41756, "lon": -0.06084, "name": "Penge West"}, {"id": "910GRTHERHI", "lat": 51.50082, "lon": -0.05205, "name": "Rotherhithe"}, {"id": "910GSHADWEL", "lat": 51.51128, "lon": -0.05693, "name": "Shadwell"}, {"id": "910GSHRDHST", "lat": 51.52338, "lon": -0.07525, "name": "Shoreditch High Street"}, {"id": "910GSURREYQ", "lat": 51.4932, "lon": -0.04752, "name": "Surrey Quays"}, {"id": "910GSYDENHM", "lat": 51.42725, "lon": -0.05424, "name": "Sydenham"}, {"id": "910GWAPPING", "lat": 51.50439, "lon": -0.05593, "name": "Wapping"}, {"id": "910GWCHAPEL", "lat": 51.51947, "lon": -0.05976, "name": "Whitechapel"}, {"id": "910GWCROYDN", "lat": 51.37843, "lon": -0.10258, "name": "West Croydon"}, {"id": "910GWNDSWRD", "lat": 51.47022, "lon": -0.13852, "name": "Wandsworth Road"}, {"id": "910GABWDXR", "lat": 51.49124, "lon": 0.12137, "name": "Abbey Wood"}, {"id": "910GACTONML", "lat": 51.51718, "lon": -0.26676, "name": "Acton Main Line"}, {"id": "910GBNHAM", "lat": 51.52351, "lon": -0.64637, "name": "Burnham (Berks)"}, {"id": "910GBONDST", "lat": 51.51369, "lon": -0.14952, "name": "Bond Street"}, {"id": "910GBRTWOOD", "lat": 51.6136, "lon": 0.29959, "name": "Brentwood"}, {"id": "910GCANWHRF", "lat": 51.50632, "lon": -0.01881, "name": "Canary Wharf"}, {"id": "910GCHDWLHT", "lat": 51.56804, "lon": 0.12896, "name": "Chadwell Heath"}, {"id": "910GCUSTMHS", "lat": 51.50984, "lon": 0.02656, "name": "Custom House"}, {"id": "910GEALINGB", "lat": 51.51484, "lon": -0.30175, "name": "Ealing Broadway"}, {"id": "910GFRNDXR", "lat": 51.51996, "lon": -0.10305, "name": "Farringdon"}, {"id": "910GFRSTGT", "lat": 51.54943, "lon": 0.02435, "name": "Forest Gate"}, {"id": "910GGIDEAPK", "lat": 51.5819, "lon": 0.20596, "name": "Gidea Park"}, {"id": "910GGODMAYS", "lat": 51.56558, "lon": 0.11081, "name": "Goodmayes"}, {"id": "910GHANWELL", "lat": 51.51183, "lon": -0.33858, "name": "Hanwell"}, {"id": "910GHAYESAH", "lat": 51.5031, "lon": -0.42068, "name": "Hayes & Harlington"}, {"id": "910GHRLDWOD", "lat": 51.59277, "lon": 0.23313, "name": "Harold Wood"}, {"id": "910GHTRWAPT", "lat": 51.47199, "lon": -0.45479, "name": "Heathrow Terminals 2 & 3"}, {"id": "910GHTRWTM4", "lat": 51.45827, "lon": -0.44546, "name": "Heathrow Terminal 4"}, {"id": "910GHTRWTM5", "lat": 51.47005, "lon": -0.49059, "name": "Heathrow Terminal 5"}, {"id": "910GILFORD", "lat": 51.55912, "lon": 0.06968, "name": "Ilford"}, {"id": "910GIVER", "lat": 51.5085, "lon": -0.50673, "name": "Iver"}, {"id": "910GLANGLEY", "lat": 51.50806, "lon": -0.54176, "name": "Langley (Berks)"}, {"id": "910GLIVSTLL", "lat": 51.51772, "lon": -0.08204, "name": "Liverpool Street"}, {"id": "910GMANRPK", "lat": 51.55248, "lon": 0.04634, "name": "Manor Park"}, {"id": "910GMDNHEAD", "lat": 51.51867, "lon": -0.72266, "name": "Maidenhead"}, {"id": "910GMRYLAND", "lat": 51.54608, "lon": 0.00581, "name": "Maryland"}, {"id": "910GPADTLL", "lat": 51.51645, "lon": -0.17711, "name": "Paddington"}, {"id": "910GPADTON", "lat": 51.516, "lon": -0.17617, "name": "London Paddington"}, {"id": "910GRDNGSTN", "lat": 51.45879, "lon": -0.97186, "name": "Reading"}, {"id": "910GSHENFLD", "lat": 51.63088, "lon": 0.32985, "name": "Shenfield"}, {"id": "910GSLOUGH", "lat": 51.51188, "lon": -0.59151, "name": "Slough"}, {"id": "910GSTHALL", "lat": 51.50596, "lon": -0.37861, "name": "Southall"}, {"id": "910GSVNKNGS", "lat": 51.56403, "lon": 0.0971, "name": "Seven Kings"}, {"id": "910GTAPLOW", "lat": 51.52356, "lon": -0.68137, "name": "Taplow"}, {"id": "910GTOTCTRD", "lat": 51.51597, "lon": -0.13024, "name": "Tottenham Court Road"}, {"id": "910GTWYFORD", "lat": 51.47553, "lon": -0.86329, "name": "Twyford"}, {"id": "910GWCHAPXR", "lat": 51.51943, "lon": -0.06019, "name": "Whitechapel"}, {"id": "910GWDRYTON", "lat": 51.51006, "lon": -0.47223, "name": "West Drayton"}, {"id": "910GWEALING", "lat": 51.51351, "lon": -0.32013, "name": "West Ealing"}, {"id": "910GWOLWXR", "lat": 51.49119, "lon": 0.07072, "name": "Woolwich"}], "edges": [{"from": "940GZZLUHAW", "to": "940GZZLUKEN", "weight": 120}, {"from": "940GZZLUKEN", "to": "940GZZLUSKT", "weight": 120}, {"from": "940GZZLUSKT", "to": "940GZZLUNWY", "weight": 120}, {"from": "940GZZLUNWY", "to": "940GZZLUWYC", "weight": 120}, {"from": "940GZZLUWYC", "to": "940GZZLUSGP", "weight": 120}, {"from": "940GZZLUSGP", "to": "940GZZLUHSN", "weight": 120}, {"from": "940GZZLUHSN", "to": "940GZZLUWJN", "weight": 120}, {"from": "940GZZLUWJN", "to": "940GZZLUKSL", "weight": 120}, {"from": "940GZZLUKSL", "to": "940GZZLUQPS", "weight": 120}, {"from": "940GZZLUQPS", "to": "940GZZLUKPK", "weight": 120}, {"from": "940GZZLUKPK", "to": "940GZZLUMVL", "weight": 120}, {"from": "940GZZLUMVL", "to": "940GZZLUWKA", "weight": 120}, {"from": "940GZZLUWKA", "to": "940GZZLUPAC", "weight": 120}, {"from": "940GZZLUPAC", "to": "940GZZLUERB", "weight": 120}, {"from": "940GZZLUERB", "to": "940GZZLUMYB", "weight": 120}, {"from": "940GZZLUMYB", "to": "940GZZLUBST", "weight": 120}, {"from": "940GZZLUBST", "to": "940GZZLURGP", "weight": 120}, {"from": "940GZZLURGP", "to": "940GZZLUOXC", "weight": 120}, {"from": "940GZZLUOXC", "to": "940GZZLUPCC", "weight": 120}, {"from": "940GZZLUPCC", "to": "940GZZLUCHX", "weight": 120}, {"from": "940GZZLUCHX", "to": "940GZZLUEMB", "weight": 120}, {"from": "940GZZLUEMB", "to": "940GZZLUWLO", "weight": 120}, {"from": "940GZZLUWLO", "to": "940GZZLULBN", "weight": 120}, {"from": "940GZZLULBN", "to": "940GZZLUEAC", "weight": 120}, {"from": "940GZZLUEPG", "to": "940GZZLUTHB", "weight": 120}, {"from": "940GZZLUTHB", "to": "940GZZLUDBN", "weight": 120}, {"from": "940GZZLUDBN", "to": "940GZZLULGN", "weight": 120}, {"from": "940GZZLULGN", "to": "940GZZLUBKH", "weight": 120}, {"from": "940GZZLUBKH", "to": "940GZZLUWOF", "weight": 120}, {"from": "940GZZLUWOF", "to": "940GZZLUSWF", "weight": 120}, {"from": "940GZZLUSWF", "to": "940GZZLUSNB", "weight": 120}, {"from": "940GZZLUSNB", "to": "940GZZLULYS", "weight": 120}, {"from": "940GZZLULYS", "to": "940GZZLULYN", "weight": 120}, {"from": "940GZZLULYN", "to": "940GZZLUSTD", "weight": 120}, {"from": "940GZZLUSTD", "to": "940GZZLUMED", "weight": 120}, {"from": "940GZZLUMED", "to": "940GZZLUBLG", "weight": 120}, {"from": "940GZZLUBLG", "to": "940GZZLULVT", "weight": 120}, {"from": "940GZZLULVT", "to": "940GZZLUBNK", "weight": 120}, {"from": "940GZZLUBNK", "to": "940GZZLUSPU", "weight": 120}, {"from": "940GZZLUSPU", "to": "940GZZLUCHL", "weight": 120}, {"from": "940GZZLUCHL", "to": "940GZZLUHBN", "weight": 120}, {"from": "940GZZLUHBN", "to": "940GZZLUTCR", "weight": 120}, {"from": "940GZZLUTCR", "to": "940GZZLUOXC", "weight": 120}, {"from": "940GZZLUOXC", "to": "940GZZLUBND", "weight": 120}, {"from": "940GZZLUBND", "to": "940GZZLUMBA", "weight": 120}, {"from": "940GZZLUMBA", "to": "940GZZLULGT", "weight": 120}, {"from": "940GZZLULGT", "to": "940GZZLUQWY", "weight": 120}, {"from": "940GZZLUQWY", "to": "940GZZLUNHG", "weight": 120}, {"from": "940GZZLUNHG", "to": "940GZZLUHPK", "weight": 120}, {"from": "940GZZLUHPK", "to": "940GZZLUSBC", "weight": 120}, {"from": "940GZZLUSBC", "to": "940GZZLUWCY", "weight": 120}, {"from": "940GZZLUWCY", "to": "940GZZLUEAN", "weight": 120}, {"from": "940GZZLUEAN", "to": "940GZZLUNAN", "weight": 120}, {"from": "940GZZLUNAN", "to": "940GZZLUHGR", "weight": 120}, {"from": "940GZZLUHGR", "to": "940GZZLUPVL", "weight": 120}, {"from": "940GZZLUPVL", "to": "940GZZLUGFD", "weight": 120}, {"from": "940GZZLUGFD", "to": "940GZZLUNHT", "weight": 120}, {"from": "940GZZLUNHT", "to": "940GZZLUSRP", "weight": 120}, {"from": "940GZZLUSRP", "to": "940GZZLURSG", "weight": 120}, {"from": "940GZZLURSG", "to": "940GZZLUWRP", "weight": 120}, {"from": "940GZZLUHLT", "to": "940GZZLUFLP", "weight": 120}, {"from": "940GZZLUFLP", "to": "940GZZLUBKE", "weight": 120}, {"from": "940GZZLUBKE", "to": "940GZZLUNBP", "weight": 120}, {"from": "940GZZLUNBP", "to": "940GZZLUGTH", "weight": 120}, {"from": "940GZZLUGTH", "to": "940GZZLURBG", "weight": 120}, {"from": "940GZZLURBG", "to": "940GZZLUWSD", "weight": 120}, {"from": "940GZZLUWSD", "to": "940GZZLULYS", "weight": 120}, {"from": "940GZZLUHLT", "to": "940GZZLUGGH", "weight": 120}, {"from": "940GZZLUGGH", "to": "940GZZLUCWL", "weight": 120}, {"from": "940GZZLUCWL", "to": "940GZZLURVY", "weight": 120}, {"from": "940GZZLURVY", "to": "940GZZLUWOF", "weight": 120}, {"from": "940GZZLUNAN", "to": "940GZZLUWTA", "weight": 120}, {"from": "940GZZLUWTA", "to": "940GZZLUEBY", "weight": 120}, {"from": "940GZZLUERC", "to": "940GZZLUPAC", "weight": 120}, {"from": "940GZZLUPAC", "to": "940GZZLUBWT", "weight": 120}, {"from": "940GZZLUBWT", "to": "940GZZLUNHG", "weight": 120}, {"from": "940GZZLUNHG", "to": "940GZZLUHSK", "weight": 120}, {"from": "940GZZLUHSK", "to": "940GZZLUGTR", "weight": 120}, {"from": "940GZZLUGTR", "to": "940GZZLUSKS", "weight": 120}, {"from": "940GZZLUSKS", "to": "940GZZLUSSQ", "weight": 120}, {"from": "940GZZLUSSQ", "to": "940GZZLUVIC", "weight": 120}, {"from": "940GZZLUVIC", "to": "940GZZLUSJP", "weight": 120}, {"from": "940GZZLUSJP", "to": "940GZZLUWSM", "weight": 120}, {"from": "940GZZLUWSM", "to": "940GZZLUEMB", "weight": 120}, {"from": "940GZZLUEMB", "to": "940GZZLUTMP", "weight": 120}, {"from": "940GZZLUTMP", "to": "940GZZLUBKF", "weight": 120}, {"from": "940GZZLUBKF", "to": "940GZZLUMSH", "weight": 120}, {"from": "940GZZLUMSH", "to": "940GZZLUCST", "weight": 120}, {"from": "940GZZLUCST", "to": "940GZZLUMMT", "weight": 120}, {"from": "940GZZLUMMT", "to": "940GZZLUTWH", "weight": 120}, {"from": "940GZZLUTWH", "to": "940GZZLUALD", "weight": 120}, {"from": "940GZZLUALD", "to": "940GZZLULVT", "weight": 120}, {"from": "940GZZLULVT", "to": "940GZZLUMGT", "weight": 120}, {"from": "940GZZLUMGT", "to": "940GZZLUBBN", "weight": 120}, {"from": "940GZZLUBBN", "to": "940GZZLUFCN", "weight": 120}, {"from": "940GZZLUFCN", "to": "940GZZLUKSX", "weight": 120}, {"from": "940GZZLUKSX", "to": "940GZZLUESQ", "weight": 120}, {"from": "940GZZLUESQ", "to": "940GZZLUGPS", "weight": 120}, {"from": "940GZZLUGPS", "to": "940GZZLUBST", "weight": 120}, {"from": "940GZZLUBST", "to": "940GZZLUERC", "weight": 120}, {"from": "940GZZLUERC", "to": "940GZZLUPAH", "weight": 120}, {"from": "940GZZLUPAH", "to": "940GZZLURYO", "weight": 120}, {"from": "940GZZLURYO", "to": "940GZZLUWSP", "weight": 120}, {"from": "940GZZLUWSP", "to": "940GZZLULAD", "weight": 120}, {"from": "940GZZLULAD", "to": "940GZZLULRD", "weight": 120}, {"from": "940GZZLULRD", "to": "940GZZLUWLA", "weight": 120}, {"from": "940GZZLUWLA", "to": "940GZZLUSBM", "weight": 120}, {"from": "940GZZLUSBM", "to": "940GZZLUGHK", "weight": 120}, {"from": "940GZZLUGHK", "to": "940GZZLUHSC", "weight": 120}, {"from": "940GZZLUUPM", "to": "940GZZLUUPB", "weight": 120}, {"from": "940GZZLUUPB", "to": "940GZZLUHCH", "weight": 120}, {"from": "940GZZLUHCH", "to": "940GZZLUEPK", "weight": 120}, {"from": "940GZZLUEPK", "to": "940GZZLUDGE", "weight": 120}, {"from": "940GZZLUDGE", "to": "940GZZLUDGY", "weight": 120}, {"from": "940GZZLUDGY", "to": "940GZZLUBEC", "weight": 120}, {"from": "940GZZLUBEC", "to": "940GZZLUUPY", "weight": 120}, {"from": "940GZZLUUPY", "to": "940GZZLUBKG", "weight": 120}, {"from": "940GZZLUBKG", "to": "940GZZLUEHM", "weight": 120}, {"from": "940GZZLUEHM", "to": "940GZZLUUPK", "weight": 120}, {"from": "940GZZLUUPK", "to": "940GZZLUPLW", "weight": 120}, {"from": "940GZZLUPLW", "to": "940GZZLUWHM", "weight": 120}, {"from": "940GZZLUWHM", "to": "940GZZLUBBB", "weight": 120}, {"from": "940GZZLUBBB", "to": "940GZZLUBWR", "weight": 120}, {"from": "940GZZLUBWR", "to": "940GZZLUMED", "weight": 120}, {"from": "940GZZLUMED", "to": "940GZZLUSGN", "weight": 120}, {"from": "940GZZLUSGN", "to": "940GZZLUWPL", "weight": 120}, {"from": "940GZZLUWPL", "to": "940GZZLUADE", "weight": 120}, {"from": "940GZZLUADE", "to": "940GZZLUTWH", "weight": 120}, {"from": "940GZZLUGTR", "to": "940GZZLUECT", "weight": 120}, {"from": "940GZZLUECT", "to": "940GZZLUWKN", "weight": 120}, {"from": "940GZZLUWKN", "to": "940GZZLUBSC", "weight": 120}, {"from": "940GZZLUBSC", "to": "940GZZLUHSD", "weight": 120}, {"from": "940GZZLUHSD", "to": "940GZZLURVP", "weight": 120}, {"from": "940GZZLURVP", "to": "940GZZLUSFB", "weight": 120}, {"from": "940GZZLUSFB", "to": "940GZZLUTNG", "weight": 120}, {"from": "940GZZLUTNG", "to": "940GZZLUCWP", "weight": 120}, {"from": "940GZZLUCWP", "to": "940GZZLUACT", "weight": 120}, {"from": "940GZZLUACT", "to": "940GZZLUECM", "weight": 120}, {"from": "940GZZLUECM", "to": "940GZZLUEBY", "weight": 120}, {"from": "940GZZLUTNG", "to": "940GZZLUGBY", "weight": 120}, {"from": "940GZZLUGBY", "to": "940GZZLUKWG", "weight": 120}, {"from": "940GZZLUKWG", "to": "940GZZLURMD", "weight": 120}, {"from": "940GZZLUECT", "to": "940GZZLUWBN", "weight": 120}, {"from": "940GZZLUWBN", "to": "940GZZLUFBY", "weight": 120}, {"from": "940GZZLUFBY", "to": "940GZZLUPSG", "weight": 120}, {"from": "940GZZLUPSG", "to": "940GZZLUPYB", "weight": 120}, {"from": "940GZZLUPYB", "to": "940GZZLUEPY", "weight": 120}, {"from": "940GZZLUEPY", "to": "940GZZLUSFS", "weight": 120}, {"from": "940GZZLUSFS", "to": "940GZZLUWIP", "weight": 120}, {"from": "940GZZLUWIP", "to": "940GZZLUWIM", "weight": 120}, {"from": "940GZZLUHSK", "to": "940GZZLUECT", "weight": 120}, {"from": "940GZZLUECT", "to": "940GZZLUKOY", "weight": 120}, {"from": "940GZZLUADE", "to": "940GZZLULVT", "weight": 120}, {"from": "940GZZLUSTD", "to": "940GZZLUWHM", "weight": 120}, {"from": "940GZZLUWHM", "to": "940GZZLUCGT", "weight": 120}, {"from": "940GZZLUCGT", "to": "940GZZLUNGW", "weight": 120}, {"from": "940GZZLUNGW", "to": "940GZZLUCYF", "weight": 120}, {"from": "940GZZLUCYF", "to": "940GZZLUCWR", "weight": 120}, {"from": "940GZZLUCWR", "to": "940GZZLUBMY", "weight": 120}, {"from": "940GZZLUBMY", "to": "940GZZLULNB", "weight": 120}, {"from": "940GZZLULNB", "to": "940GZZLUSWK", "weight": 120}, {"from": "940GZZLUSWK", "to": "940GZZLUWLO", "weight": 120}, {"from": "940GZZLUWLO", "to": "940GZZLUWSM", "weight": 120}, {"from": "940GZZLUWSM", "to": "940GZZLUGPK", "weight": 120}, {"from": "940GZZLUGPK", "to": "940GZZLUBND", "weight": 120}, {"from": "940GZZLUBND", "to": "940GZZLUBST", "weight": 120}, {"from": "940GZZLUBST", "to": "940GZZLUSJW", "weight": 120}, {"from": "940GZZLUSJW", "to": "940GZZLUSWC", "weight": 120}, {"from": "940GZZLUSWC", "to": "940GZZLUFYR", "weight": 120}, {"from": "940GZZLUFYR", "to": "940GZZLUWHP", "weight": 120}, {"from": "940GZZLUWHP", "to": "940GZZLUKBN", "weight": 120}, {"from": "940GZZLUKBN", "to": "940GZZLUWIG", "weight": 120}, {"from": "940GZZLUWIG", "to": "940GZZLUDOH", "weight": 120}, {"from": "940GZZLUDOH", "to": "940GZZLUNDN", "weight": 120}, {"from": "940GZZLUNDN", "to": "940GZZLUWYP", "weight": 120}, {"from": "940GZZLUWYP", "to": "940GZZLUKBY", "weight": 120}, {"from": "940GZZLUKBY", "to": "940GZZLUQBY", "weight": 120}, {"from": "940GZZLUQBY", "to": "940GZZLUCPK", "weight": 120}, {"from": "940GZZLUCPK", "to": "940GZZLUSTM", "weight": 120}, {"from": "940GZZLUBST", "to": "940GZZLUFYR", "weight": 120}, {"from": "940GZZLUFYR", "to": "940GZZLUWYP", "weight": 120}, {"from": "940GZZLUWYP", "to": "940GZZLUPRD", "weight": 120}, {"from": "940GZZLUPRD", "to": "940GZZLUNKP", "weight": 120}, {"from": "940GZZLUNKP", "to": "940GZZLUHOH", "weight": 120}, {"from": "940GZZLUHOH", "to": "940GZZLUNHA", "weight": 120}, {"from": "940GZZLUNHA", "to": "940GZZLUPNR", "weight": 120}, {"from": "940GZZLUPNR", "to": "940GZZLUNWH", "weight": 120}, {"from": "940GZZLUNWH", "to": "940GZZLUNOW", "weight": 120}, {"from": "940GZZLUNOW", "to": "940GZZLUMPK", "weight": 120}, {"from": "940GZZLUMPK", "to": "940GZZLURKW", "weight": 120}, {"from": "940GZZLURKW", "to": "940GZZLUCYD", "weight": 120}, {"from": "940GZZLUCYD", "to": "940GZZLUCAL", "weight": 120}, {"from": "940GZZLUCAL", "to": "940GZZLUCSM", "weight": 120}, {"from": "940GZZLUCAL", "to": "940GZZLUAMS", "weight": 120}, {"from": "940GZZLUHOH", "to": "940GZZLUWHW", "weight": 120}, {"from": "940GZZLUWHW", "to": "940GZZLURYL", "weight": 120}, {"from": "940GZZLURYL", "to": "940GZZLUEAE", "weight": 120}, {"from": "940GZZLUEAE", "to": "940GZZLURSM", "weight": 120}, {"from": "940GZZLURSM", "to": "940GZZLURSP", "weight": 120}, {"from": "940GZZLURSP", "to": "940GZZLUICK", "weight": 120}, {"from": "940GZZLUICK", "to": "940GZZLUHGD", "weight": 120}, {"from": "940GZZLUHGD", "to": "940GZZLUUXB", "weight": 120}, {"from": "940GZZLUMPK", "to": "940GZZLUCXY", "weight": 120}, {"from": "940GZZLUCXY", "to": "940GZZLUWAF", "weight": 120}, {"from": "940GZZLUHBT", "to": "940GZZLUTAW", "weight": 120}, {"from": "940GZZLUTAW", "to": "940GZZLUWOP", "weight": 120}, {"from": "940GZZLUWOP", "to": "940GZZLUWFN", "weight": 120}, {"from": "940GZZLUWFN", "to": "940GZZLUFYC", "weight": 120}, {"from": "940GZZLUFYC", "to": "940GZZLUEFY", "weight": 120}, {"from": "940GZZLUEFY", "to": "940GZZLUHGT", "weight": 120}, {"from": "940GZZLUHGT", "to": "940GZZLUACY", "weight": 120}, {"from": "940GZZLUACY", "to": "940GZZLUTFP", "weight": 120}, {"from": "940GZZLUTFP", "to": "940GZZLUKSH", "weight": 120}, {"from": "940GZZLUKSH", "to": "940GZZLUCTN", "weight": 120}, {"from": "940GZZLUCTN", "to": "940GZZLUMTC", "weight": 120}, {"from": "940GZZLUMTC", "to": "940GZZLUEUS", "weight": 120}, {"from": "940GZZLUEUS", "to": "940GZZLUWRR", "weight": 120}, {"from": "940GZZLUWRR", "to": "940GZZLUGDG", "weight": 120}, {"from": "940GZZLUGDG", "to": "940GZZLUTCR", "weight": 120}, {"from": "940GZZLUTCR", "to": "940GZZLULSQ", "weight": 120}, {"from": "940GZZLULSQ", "to": "940GZZLUCHX", "weight": 120}, {"from": "940GZZLUWLO", "to": "940GZZLUKNG", "weight": 120}, {"from": "940GZZLUKNG", "to": "940GZZLUOVL", "weight": 120}, {"from": "940GZZLUOVL", "to": "940GZZLUSKW", "weight": 120}, {"from": "940GZZLUSKW", "to": "940GZZLUCPN", "weight": 120}, {"from": "940GZZLUCPN", "to": "940GZZLUCPC", "weight": 120}, {"from": "940GZZLUCPC", "to": "940GZZLUCPS", "weight": 120}, {"from": "940GZZLUCPS", "to": "940GZZLUBLM", "weight": 120}, {"from": "940GZZLUBLM", "to": "940GZZLUTBC", "weight": 120}, {"from": "940GZZLUTBC", "to": "940GZZLUTBY", "weight": 120}, {"from": "940GZZLUTBY", "to": "940GZZLUCSD", "weight": 120}, {"from": "940GZZLUCSD", "to": "940GZZLUSWN", "weight": 120}, {"from": "940GZZLUSWN", "to": "940GZZLUMDN", "weight": 120}, {"from": "940GZZLUCTN", "to": "940GZZLUEUS", "weight": 120}, {"from": "940GZZLUEUS", "to": "940GZZLUKSX", "weight": 120}, {"from": "940GZZLUKSX", "to": "940GZZLUAGL", "weight": 120}, {"from": "940GZZLUAGL", "to": "940GZZLUODS", "weight": 120}, {"from": "940GZZLUODS", "to": "940GZZLUMGT", "weight": 120}, {"from": "940GZZLUMGT", "to": "940GZZLUBNK", "weight": 120}, {"from": "940GZZLUBNK", "to": "940GZZLULNB", "weight": 120}, {"from": "940GZZLULNB", "to": "940GZZLUBOR", "weight": 120}, {"from": "940GZZLUBOR", "to": "940GZZLUEAC", "weight": 120}, {"from": "940GZZLUEAC", "to": "940GZZLUKNG", "weight": 120}, {"from": "940GZZLUEGW", "to": "940GZZLUBTK", "weight": 120}, {"from": "940GZZLUBTK", "to": "940GZZLUCND", "weight": 120}, {"from": "940GZZLUCND", "to": "940GZZLUHCL", "weight": 120}, {"from": "940GZZLUHCL", "to": "940GZZLUBTX", "weight": 120}, {"from": "940GZZLUBTX", "to": "940GZZLUGGN", "weight": 120}, {"from": "940GZZLUGGN", "to": "940GZZLUHTD", "weight": 120}, {"from": "940GZZLUHTD", "to": "940GZZLUBZP", "weight": 120}, {"from": "940GZZLUBZP", "to": "940GZZLUCFM", "weight": 120}, {"from": "940GZZLUCFM", "to": "940GZZLUCTN", "weight": 120}, {"from": "940GZZLUMHL", "to": "940GZZLUFYC", "weight": 120}, {"from": "940GZZLUKNG", "to": "940GZZNEUGST", "weight": 120}, {"from": "940GZZNEUGST", "to": "940GZZBPSUST", "weight": 120}, {"from": "940GZZLUCKS", "to": "940GZZLUOAK", "weight": 120}, {"from": "940GZZLUOAK", "to": "940GZZLUSGT", "weight": 120}, {"from": "940GZZLUSGT", "to": "940GZZLUASG", "weight": 120}, {"from": "940GZZLUASG", "to": "940GZZLUBDS", "weight": 120}, {"from": "940GZZLUBDS", "to": "940GZZLUWOG", "weight": 120}, {"from": "940GZZLUWOG", "to": "940GZZLUTPN", "weight": 120}, {"from": "940GZZLUTPN", "to": "940GZZLUMRH", "weight": 120}, {"from": "940GZZLUMRH", "to": "940GZZLUFPK", "weight": 120}, {"from": "940GZZLUFPK", "to": "940GZZLUASL", "weight": 120}, {"from": "940GZZLUASL", "to": "940GZZLUHWY", "weight": 120}, {"from": "940GZZLUHWY", "to": "940GZZLUCAR", "weight": 120}, {"from": "940GZZLUCAR", "to": "940GZZLUKSX", "weight": 120}, {"from": "940GZZLUKSX", "to": "940GZZLURSQ", "weight": 120}, {"from": "940GZZLURSQ", "to": "940GZZLUHBN", "weight": 120}, {"from": "940GZZLUHBN", "to": "940GZZLUCGN", "weight": 120}, {"from": "940GZZLUCGN", "to": "940GZZLULSQ", "weight": 120}, {"from": "940GZZLULSQ", "to": "940GZZLUPCC", "weight": 120}, {"from": "940GZZLUPCC", "to": "940GZZLUGPK", "weight": 120}, {"from": "940GZZLUGPK", "to": "940GZZLUHPC", "weight": 120}, {"from": "940GZZLUHPC", "to": "940GZZLUKNB", "weight": 120}, {"from": "940GZZLUKNB", "to": "940GZZLUSKS", "weight": 120}, {"from": "940GZZLUECT", "to": "940GZZLUBSC", "weight": 120}, {"from": "940GZZLUHSD", "to": "940GZZLUTNG", "weight": 120}, {"from": "940GZZLUTNG", "to": "940GZZLUACT", "weight": 120}, {"from": "940GZZLUECM", "to": "940GZZLUNEN", "weight": 120}, {"from": "940GZZLUNEN", "to": "940GZZLUPKR", "weight": 120}, {"from": "940GZZLUPKR", "to": "940GZZLUALP", "weight": 120}, {"from": "940GZZLUALP", "to": "940GZZLUSUT", "weight": 120}, {"from": "940GZZLUSUT", "to": "940GZZLUSUH", "weight": 120}, {"from": "940GZZLUSUH", "to": "940GZZLUSHH", "weight": 120}, {"from": "940GZZLUSHH", "to": "940GZZLURYL", "weight": 120}, {"from": "940GZZLUACT", "to": "940GZZLUSEA", "weight": 120}, {"from": "940GZZLUSEA", "to": "940GZZLUNFD", "weight": 120}, {"from": "940GZZLUNFD", "to": "940GZZLUBOS", "weight": 120}, {"from": "940GZZLUBOS", "to": "940GZZLUOSY", "weight": 120}, {"from": "940GZZLUOSY", "to": "940GZZLUHWE", "weight": 120}, {"from": "940GZZLUHWE", "to": "940GZZLUHWC", "weight": 120}, {"from": "940GZZLUHWC", "to": "940GZZLUHWT", "weight": 120}, {"from": "940GZZLUHWT", "to": "940GZZLUHNX", "weight": 120}, {"from": "940GZZLUHNX", "to": "940GZZLUHRC", "weight": 120}, {"from": "940GZZLUHRC", "to": "940GZZLUHR5", "weight": 120}, {"from": "940GZZLUHR4", "to": "940GZZLUHRC", "weight": 120}, {"from": "940GZZLUHNX", "to": "940GZZLUHR4", "weight": 120}, {"from": "940GZZLUWWL", "to": "940GZZLUBLR", "weight": 120}, {"from": "940GZZLUBLR", "to": "940GZZLUTMH", "weight": 120}, {"from": "940GZZLUTMH", "to": "940GZZLUSVS", "weight": 120}, {"from": "940GZZLUSVS", "to": "940GZZLUFPK", "weight": 120}, {"from": "940GZZLUFPK", "to": "940GZZLUHAI", "weight": 120}, {"from": "940GZZLUHAI", "to": "940GZZLUKSX", "weight": 120}, {"from": "940GZZLUWRR", "to": "940GZZLUOXC", "weight": 120}, {"from": "940GZZLUOXC", "to": "940GZZLUGPK", "weight": 120}, {"from": "940GZZLUGPK", "to": "940GZZLUVIC", "weight": 120}, {"from": "940GZZLUVIC", "to": "940GZZLUPCO", "weight": 120}, {"from": "940GZZLUPCO", "to": "940GZZLUVXL", "weight": 120}, {"from": "940GZZLUVXL", "to": "940GZZLUSKW", "weight": 120}, {"from": "940GZZLUSKW", "to": "940GZZLUBXN", "weight": 120}, {"from": "940GZZLUBNK", "to": "940GZZLUWLO", "weight": 120}, {"from": "940GZZDLLEW", "to": "940GZZDLELV", "weight": 120}, {"from": "940GZZDLELV", "to": "940GZZDLDEP", "weight": 120}, {"from": "940GZZDLDEP", "to": "940GZZDLGRE", "weight": 120}, {"from": "940GZZDLGRE", "to": "940GZZDLCUT", "weight": 120}, {"from": "940GZZDLCUT", "to": "940GZZDLISL", "weight": 120}, {"from": "940GZZDLISL", "to": "940GZZDLMUD", "weight": 120}, {"from": "940GZZDLMUD", "to": "940GZZDLCLA", "weight": 120}, {"from": "940GZZDLCLA", "to": "940GZZDLSOQ", "weight": 120}, {"from": "940GZZDLSOQ", "to": "940GZZDLHEQ", "weight": 120}, {"from": "940GZZDLHEQ", "to": "940GZZDLCAN", "weight": 120}, {"from": "940GZZDLCAN", "to": "940GZZDLWIQ", "weight": 120}, {"from": "940GZZDLWIQ", "to": "940GZZDLPOP", "weight": 120}, {"from": "940GZZDLPOP", "to": "940GZZDLALL", "weight": 120}, {"from": "940GZZDLALL", "to": "940GZZDLLDP", "weight": 120}, {"from": "940GZZDLLDP", "to": "940GZZDLDEV", "weight": 120}, {"from": "940GZZDLDEV", "to": "940GZZDLBOW", "weight": 120}, {"from": "940GZZDLBOW", "to": "940GZZDLPUD", "weight": 120}, {"from": "940GZZDLPUD", "to": "940GZZDLSTD", "weight": 120}, {"from": "940GZZDLWIQ", "to": "940GZZDLWFE", "weight": 120}, {"from": "940GZZDLWFE", "to": "940GZZDLLIM", "weight": 120}, {"from": "940GZZDLLIM", "to": "940GZZDLSHA", "weight": 120}, {"from": "940GZZDLSHA", "to": "940GZZDLBNK", "weight": 120}, {"from": "940GZZDLSHA", "to": "940GZZDLTWG", "weight": 120}, {"from": "940GZZDLBEC", "to": "940GZZDLGAL", "weight": 120}, {"from": "940GZZDLGAL", "to": "940GZZDLCYP", "weight": 120}, {"from": "940GZZDLCYP", "to": "940GZZDLBPK", "weight": 120}, {"from": "940GZZDLBPK", "to": "940GZZDLRAL", "weight": 120}, {"from": "940GZZDLRAL", "to": "940GZZDLPRE", "weight": 120}, {"from": "940GZZDLPRE", "to": "940GZZDLCUS", "weight": 120}, {"from": "940GZZDLCUS", "to": "940GZZDLRVC", "weight": 120}, {"from": "940GZZDLRVC", "to": "940GZZDLCGT", "weight": 120}, {"from": "940GZZDLCGT", "to": "940GZZDLEIN", "weight": 120}, {"from": "940GZZDLEIN", "to": "940GZZDLBLA", "weight": 120}, {"from": "940GZZDLBLA", "to": "940GZZDLPOP", "weight": 120}, {"from": "940GZZDLPOP", "to": "940GZZDLWFE", "weight": 120}, {"from": "940GZZDLWFE", "to": "940GZZDLCAN", "weight": 120}, {"from": "940GZZDLWLA", "to": "940GZZDLKGV", "weight": 120}, {"from": "940GZZDLKGV", "to": "940GZZDLLCA", "weight": 120}, {"from": "940GZZDLLCA", "to": "940GZZDLPDK", "weight": 120}, {"from": "940GZZDLPDK", "to": "940GZZDLWSV", "weight": 120}, {"from": "940GZZDLWSV", "to": "940GZZDLCGT", "weight": 120}, {"from": "940GZZDLCGT", "to": "940GZZDLSTL", "weight": 120}, {"from": "940GZZDLSTL", "to": "940GZZDLWHM", "weight": 120}, {"from": "940GZZDLWHM", "to": "940GZZDLABR", "weight": 120}, {"from": "940GZZDLABR", "to": "940GZZDLSHS", "weight": 120}, {"from": "940GZZDLSHS", "to": "940GZZDLSTD", "weight": 120}, {"from": "940GZZDLSTD", "to": "940GZZDLSIT", "weight": 120}, {"from": "910GUPMNSTR", "to": "910GEMRSPKH", "weight": 120}, {"from": "910GEMRSPKH", "to": "910GROMFORD", "weight": 120}, {"from": "910GWATFJDC", "to": "910GWATFDHS", "weight": 120}, {"from": "910GWATFDHS", "to": "910GBUSHYDC", "weight": 120}, {"from": "910GBUSHYDC", "to": "910GCRPNDPK", "weight": 120}, {"from": "910GCRPNDPK", "to": "910GHTCHEND", "weight": 120}, {"from": "910GHTCHEND", "to": "910GHEDSTNL", "weight": 120}, {"from": "910GHEDSTNL", "to": "910GHROW", "weight": 120}, {"from": "910GHROW", "to": "910GKTON", "weight": 120}, {"from": "910GKTON", "to": "910GSKENTON", "weight": 120}, {"from": "910GSKENTON", "to": "910GNWEMBLY", "weight": 120}, {"from": "910GNWEMBLY", "to": "910GWMBY", "weight": 120}, {"from": "910GWMBY", "to": "910GSTNBGPK", "weight": 120}, {"from": "910GSTNBGPK", "to": "910GHARLSDN", "weight": 120}, {"from": "910GHARLSDN", "to": "910GWLSDJHL", "weight": 120}, {"from": "910GWLSDJHL", "to": "910GKENSLG", "weight": 120}, {"from": "910GKENSLG", "to": "910GQPRK", "weight": 120}, {"from": "910GQPRK", "to": "910GKLBRNHR", "weight": 120}, {"from": "910GKLBRNHR", "to": "910GSHMPSTD", "weight": 120}, {"from": "910GSHMPSTD", "to": "910GEUSTON", "weight": 120}, {"from": "910GRICHMND", "to": "910GKEWGRDN", "weight": 120}, {"from": "910GKEWGRDN", "to": "910GGNRSBRY", "weight": 120}, {"from": "910GGNRSBRY", "to": "910GSACTON", "weight": 120}, {"from": "910GSACTON", "to": "910GACTNCTL", "weight": 120}, {"from": "910GACTNCTL", "to": "910GWLSDJHL", "weight": 120}, {"from": "910GWLSDJHL", "to": "910GKENR", "weight": 120}, {"from": "910GKENR", "to": "910GBRBYPK", "weight": 120}, {"from": "910GBRBYPK", "to": "910GBRBY", "weight": 120}, {"from": "910GBRBY", "to": "910GWHMDSTD", "weight": 120}, {"from": "910GWHMDSTD", "to": "910GFNCHLYR", "weight": 120}, {"from": "910GFNCHLYR", "to": "910GHMPSTDH", "weight": 120}, {"from": "910GHMPSTDH", "to": "910GGOSPLOK", "weight": 120}, {"from": "910GGOSPLOK", "to": "910GKNTSHTW", "weight": 120}, {"from": "910GKNTSHTW", "to": "910GCMDNRD", "weight": 120}, {"from": "910GCMDNRD", "to": "910GCLDNNRB", "weight": 120}, {"from": "910GCLDNNRB", "to": "910GHGHI", "weight": 120}, {"from": "910GHGHI", "to": "910GCNNB", "weight": 120}, {"from": "910GCNNB", "to": "910GDALSKLD", "weight": 120}, {"from": "910GDALSKLD", "to": "910GHACKNYC", "weight": 120}, {"from": "910GHACKNYC", "to": "910GHOMRTON", "weight": 120}, {"from": "910GHOMRTON", "to": "910GHACKNYW", "weight": 120}, {"from": "910GHACKNYW", "to": "910GSTFD", "weight": 120}, {"from": "910GCLPHMJ1", "to": "910GCSEAH", "weight": 120}, {"from": "910GCSEAH", "to": "910GWBRMPTN", "weight": 120}, {"from": "910GWBRMPTN", "to": "910GKENOLYM", "weight": 120}, {"from": "910GKENOLYM", "to": "910GSHPDSB", "weight": 120}, {"from": "910GSHPDSB", "to": "910GWLSDJHL", "weight": 120}, {"from": "910GCSEAH", "to": "910GCLPHMJC", "weight": 120}, {"from": "910GBKRVS", "to": "910GBARKING", "weight": 120}, {"from": "910GBARKING", "to": "910GWDGRNPK", "weight": 120}, {"from": "910GWDGRNPK", "to": "910GWNSTDPK", "weight": 120}, {"from": "910GWNSTDPK", "to": "910GLYTNSHR", "weight": 120}, {"from": "910GLYTNSHR", "to": "910GLEYTNMR", "weight": 120}, {"from": "910GLEYTNMR", "to": "910GWLTHQRD", "weight": 120}, {"from": "910GWLTHQRD", "to": "910GBLCHSRD", "weight": 120}, {"from": "910GBLCHSRD", "to": "910GSTOTNHM", "weight": 120}, {"from": "910GSTOTNHM", "to": "910GHRGYGL", "weight": 120}, {"from": "910GHRGYGL", "to": "910GCROUCHH", "weight": 120}, {"from": "910GCROUCHH", "to": "910GUPRHLWY", "weight": 120}, {"from": "910GUPRHLWY", "to": "910GGOSPLOK", "weight": 120}, {"from": "910GCHESHNT", "to": "910GTHBLDSG", "weight": 120}, {"from": "910GTHBLDSG", "to": "910GTURKYST", "weight": 120}, {"from": "910GTURKYST", "to": "910GSBURY", "weight": 120}, {"from": "910GSBURY", "to": "910GEDMNGRN", "weight": 120}, {"from": "910GEDMNGRN", "to": "910GSIVRST", "weight": 120}, {"from": "910GSIVRST", "to": "910GWHHRTLA", "weight": 120}, {"from": "910GWHHRTLA", "to": "910GBRUCGRV", "weight": 120}, {"from": "910GBRUCGRV", "to": "910GSEVNSIS", "weight": 120}, {"from": "910GSEVNSIS", "to": "910GSTMFDHL", "weight": 120}, {"from": "910GSTMFDHL", "to": "910GSTKNWNG", "weight": 120}, {"from": "910GSTKNWNG", "to": "910GRCTRYRD", "weight": 120}, {"from": "910GRCTRYRD", "to": "910GHAKNYNM", "weight": 120}, {"from": "910GHAKNYNM", "to": "910GLONFLDS", "weight": 120}, {"from": "910GLONFLDS", "to": "910GCAMHTH", "weight": 120}, {"from": "910GCAMHTH", "to": "910GBTHNLGR", "weight": 120}, {"from": "910GBTHNLGR", "to": "910GLIVST", "weight": 120}, {"from": "910GENFLDTN", "to": "910GBHILLPK", "weight": 120}, {"from": "910GBHILLPK", "to": "910GEDMNGRN", "weight": 120}, {"from": "910GCHINGFD", "to": "910GHGHMSPK", "weight": 120}, {"from": "910GHGHMSPK", "to": "910GWDST", "weight": 120}, {"from": "910GWDST", "to": "910GWLTWCEN", "weight": 120}, {"from": "910GWLTWCEN", "to": "910GSTJMSST", "weight": 120}, {"from": "910GSTJMSST", "to": "910GCLAPTON", "weight": 120}, {"from": "910GCLAPTON", "to": "910GHAKNYNM", "weight": 120}, {"from": "910GWCROYDN", "to": "910GNORWDJ", "weight": 120}, {"from": "910GNORWDJ", "to": "910GANERLEY", "weight": 120}, {"from": "910GANERLEY", "to": "910GPENEW", "weight": 120}, {"from": "910GPENEW", "to": "910GSYDENHM", "weight": 120}, {"from": "910GSYDENHM", "to": "910GFORESTH", "weight": 120}, {"from": "910GFORESTH", "to": "910GHONROPK", "weight": 120}, {"from": "910GHONROPK", "to": "910GBROCKLY", "weight": 120}, {"from": "910GBROCKLY", "to": "910GNEWXGTE", "weight": 120}, {"from": "910GNEWXGTE", "to": "910GSURREYQ", "weight": 120}, {"from": "910GSURREYQ", "to": "910GCNDAW", "weight": 120}, {"from": "910GCNDAW", "to": "910GRTHERHI", "weight": 120}, {"from": "910GRTHERHI", "to": "910GWAPPING", "weight": 120}, {"from": "910GWAPPING", "to": "910GSHADWEL", "weight": 120}, {"from": "910GSHADWEL", "to": "910GWCHAPEL", "weight": 120}, {"from": "910GWCHAPEL", "to": "910GSHRDHST", "weight": 120}, {"from": "910GSHRDHST", "to": "910GHOXTON", "weight": 120}, {"from": "910GHOXTON", "to": "910GHAGGERS", "weight": 120}, {"from": "910GHAGGERS", "to": "910GDALS", "weight": 120}, {"from": "910GDALS", "to": "910GCNNB", "weight": 120}, {"from": "910GCLPHMJ1", "to": "910GWNDSWRD", "weight": 120}, {"from": "910GWNDSWRD", "to": "910GCLPHHS", "weight": 120}, {"from": "910GCLPHHS", "to": "910GDENMRKH", "weight": 120}, {"from": "910GDENMRKH", "to": "910GPCKHMRY", "weight": 120}, {"from": "910GPCKHMRY", "to": "910GPCKHMQD", "weight": 120}, {"from": "910GPCKHMQD", "to": "910GSURREYQ", "weight": 120}, {"from": "910GCRYSTLP", "to": "910GSYDENHM", "weight": 120}, {"from": "910GNWCRELL", "to": "910GSURREYQ", "weight": 120}, {"from": "910GHTRWTM4", "to": "910GHTRWAPT", "weight": 120}, {"from": "910GHTRWAPT", "to": "910GHAYESAH", "weight": 120}, {"from": "910GHAYESAH", "to": "910GSTHALL", "weight": 120}, {"from": "910GSTHALL", "to": "910GHANWELL", "weight": 120}, {"from": "910GHANWELL", "to": "910GWEALING", "weight": 120}, {"from": "910GWEALING", "to": "910GEALINGB", "weight": 120}, {"from": "910GEALINGB", "to": "910GACTONML", "weight": 120}, {"from": "910GACTONML", "to": "910GPADTLL", "weight": 120}, {"from": "910GPADTLL", "to": "910GBONDST", "weight": 120}, {"from": "910GBONDST", "to": "910GTOTCTRD", "weight": 120}, {"from": "910GTOTCTRD", "to": "910GFRNDXR", "weight": 120}, {"from": "910GFRNDXR", "to": "910GLIVSTLL", "weight": 120}, {"from": "910GLIVSTLL", "to": "910GWCHAPXR", "weight": 120}, {"from": "910GWCHAPXR", "to": "910GSTFD", "weight": 120}, {"from": "910GSTFD", "to": "910GMRYLAND", "weight": 120}, {"from": "910GMRYLAND", "to": "910GFRSTGT", "weight": 120}, {"from": "910GFRSTGT", "to": "910GMANRPK", "weight": 120}, {"from": "910GMANRPK", "to": "910GILFORD", "weight": 120}, {"from": "910GILFORD", "to": "910GSVNKNGS", "weight": 120}, {"from": "910GSVNKNGS", "to": "910GGODMAYS", "weight": 120}, {"from": "910GGODMAYS", "to": "910GCHDWLHT", "weight": 120}, {"from": "910GCHDWLHT", "to": "910GROMFORD", "weight": 120}, {"from": "910GROMFORD", "to": "910GGIDEAPK", "weight": 120}, {"from": "910GGIDEAPK", "to": "910GHRLDWOD", "weight": 120}, {"from": "910GHRLDWOD", "to": "910GBRTWOOD", "weight": 120}, {"from": "910GBRTWOOD", "to": "910GSHENFLD", "weight": 120}, {"from": "910GHTRWTM5", "to": "910GHTRWAPT", "weight": 120}, {"from": "910GWCHAPXR", "to": "910GCANWHRF", "weight": 120}, {"from": "910GCANWHRF", "to": "910GCUSTMHS", "weight": 120}, {"from": "910GCUSTMHS", "to": "910GWOLWXR", "weight": 120}, {"from": "910GWOLWXR", "to": "910GABWDXR", "weight": 120}, {"from": "910GRDNGSTN", "to": "910GTWYFORD", "weight": 120}, {"from": "910GTWYFORD", "to": "910GMDNHEAD", "weight": 120}, {"from": "910GMDNHEAD", "to": "910GTAPLOW", "weight": 120}, {"from": "910GTAPLOW", "to": "910GBNHAM", "weight": 120}, {"from": "910GBNHAM", "to": "910GSLOUGH", "weight": 120}, {"from": "910GSLOUGH", "to": "910GLANGLEY", "weight": 120}, {"from": "910GLANGLEY", "to": "910GIVER", "weight": 120}, {"from": "910GIVER", "to": "910GWDRYTON", "weight": 120}, {"from": "910GWDRYTON", "to": "910GHAYESAH", "weight": 120}, {"from": "910GACTONML", "to": "910GPADTON", "weight": 120}, {"from": "910GLIVST", "to": "910GSTFD", "weight": 120}]}